mseep_bayesian_mcp-0.1.0.dist-info/licenses/LICENSE
src/__init__.py
src/main.py
src/bayesian_engine/__init__.py
src/bayesian_engine/distributions.py
src/bayesian_engine/engine.py
src/mcp/__init__.py
src/mcp/handlers.py
src/mcp/server.py
src/schemas/__init__.py
src/schemas/mcp_schemas.py
src/utils/__init__.py
src/utils/plotting.py
mseep_bayesian_mcp-0.1.0.dist-info/METADATA
mseep_bayesian_mcp-0.1.0.dist-info/WHEEL
mseep_bayesian_mcp-0.1.0.dist-info/top_level.txt
mseep_bayesian_mcp-0.1.0.dist-info/RECORD
