Metadata-Version: 2.4
Name: mseep-bayesian-mcp
Version: 0.1.0
Summary: Bayesian reasoning MCP server for LLMs
Home-page: https://github.com/mseep
Author: mseep
Author-email: support@skydeck.ai
Maintainer: mseep
Maintainer-email: support@skydeck.ai
Keywords: mseep
Classifier: Programming Language :: Python :: 3
Classifier: License :: OSI Approved :: MIT License
Classifier: Operating System :: OS Independent
Requires-Python: >=3.6
License-File: LICENSE
Requires-Dist: pymc>=5.0.0
Requires-Dist: arviz>=0.14.0
Requires-Dist: numpy>=1.20.0
Requires-Dist: pydantic>=2.0.0
Requires-Dist: mcp>=1.6.0
Requires-Dist: fastapi>=0.100.0
Requires-Dist: matplotlib>=3.5.0
Dynamic: author
Dynamic: author-email
Dynamic: classifier
Dynamic: description
Dynamic: description-content-type
Dynamic: home-page
Dynamic: keywords
Dynamic: license-file
Dynamic: maintainer
Dynamic: maintainer-email
Dynamic: requires-dist
Dynamic: requires-python
Dynamic: summary
